setup.py
cubey/__init__.py
cubey/cubey.py
cubey.egg-info/PKG-INFO
cubey.egg-info/SOURCES.txt
cubey.egg-info/dependency_links.txt
cubey.egg-info/not-zip-safe
cubey.egg-info/top_level.txt