Metadata-Version: 1.0
Name: cubey
Version: 1.0
Summary: A fully functional puzzle cube written in python.
Home-page: http://github.com/tylermzeller/cubey
Author: Tyler Zeller
Author-email: tylermzeller@gmail.com
License: MIT
Platform: UNKNOWN
